AUTHORS
CHANGES
LICENSE
MANIFEST.in
README
TODO
requirements.txt
setup.py
djangocms_minecraft/__init__.py
djangocms_minecraft/__init__.pyc
djangocms_minecraft/cli.py
djangocms_minecraft/cli.pyc
djangocms_minecraft/cms_plugins.py
djangocms_minecraft/cms_plugins.pyc
djangocms_minecraft/models.py
djangocms_minecraft/models.pyc
djangocms_minecraft/query.py
djangocms_minecraft/query.pyc
djangocms_minecraft.egg-info/PKG-INFO
djangocms_minecraft.egg-info/SOURCES.txt
djangocms_minecraft.egg-info/dependency_links.txt
djangocms_minecraft.egg-info/entry_points.txt
djangocms_minecraft.egg-info/not-zip-safe
djangocms_minecraft.egg-info/requires.txt
djangocms_minecraft.egg-info/top_level.txt
djangocms_minecraft/migrations/0001_initial.py
djangocms_minecraft/migrations/0001_initial.pyc
djangocms_minecraft/migrations/0002_auto__add_minecraftserver.py
djangocms_minecraft/migrations/0002_auto__add_minecraftserver.pyc
djangocms_minecraft/migrations/0003_auto__del_serverstatus__del_serverquery__del_pluginslist.py
djangocms_minecraft/migrations/0003_auto__del_serverstatus__del_serverquery__del_pluginslist.pyc
djangocms_minecraft/migrations/0004_auto__chg_field_minecraftserver_map_url__chg_field_minecraftserver_mch.py
djangocms_minecraft/migrations/__init__.py
djangocms_minecraft/migrations/__init__.pyc
djangocms_minecraft/src/up_down_icon.svg
djangocms_minecraft/static/djangocms_minecraft/img/server_down_icon.png
djangocms_minecraft/static/djangocms_minecraft/img/server_up_icon.png
djangocms_minecraft/templates/minecraft/plugins_list.html
djangocms_minecraft/templates/minecraft/server_query.html
djangocms_minecraft/templates/minecraft/server_status.html