Metadata-Version: 1.1
Name: djangocms-minecraft
Version: 0.2.1
Summary: A set of Django plugins that will display live Minecraft server status and information within your project.
Home-page: https://bitbucket.org/oddotterco/djangocms-minecraft
Author: The NetYeti
Author-email: thenetyeti@oddotter.com
License: UNKNOWN
Keywords: django,cms,minecraft
Platform: Linux
Classifier: Development Status :: 4 - Beta
Classifier: Environment :: Web Environment
Classifier: Framework :: Django
Classifier: Intended Audience :: Developers
Classifier: License :: Public Domain
Classifier: Natural Language :: English
Classifier: Operating System :: OS Independent
Classifier: Programming Language :: Python :: 2.7
Classifier: Topic :: Games/Entertainment :: Multi-User Dungeons (MUD)
